<?xml version="1.0" encoding="UTF-8"?>
<beans xmlns="http://www.springframework.org/schema/beans"
       xmlns:xsi="http://www.w3.org/2001/XMLSchema-instance"
       xmlns:configure="http://www.springframework.org/schema/util"
       xmlns:context="http://www.springframework.org/schema/context"
       xmlns:util="http://www.springframework.org/schema/util"
       xsi:schemaLocation="http://www.springframework.org/schema/beans http://www.springframework.org/schema/beans/spring-beans.xsd
       http://www.springframework.org/schema/util http://www.springframework.org/schema/util/spring-util-2.0.xsd
       http://www.springframework.org/schema/context http://www.springframework.org/schema/context/spring-context-3.1.xsd">

    <!-- Root Context: defines shared resources visible to all other web components -->
    <context:component-scan base-package="uk.ac.ebi.pride.archive.security.project,
                                          uk.ac.ebi.pride.archive.security.user,
                                          uk.ac.ebi.pride.archive.repo"/>

    <!-- App Config: defines shared resources visible to all other web components -->
    <bean id="prideEmailNotifier" class="uk.ac.ebi.pride.archive.submission.util.PrideEmailNotifier">
        <constructor-arg name="mailSender" ref="mailSender"/>
        <constructor-arg name="templateMessage" ref="templateMessage"/>
    </bean>

    <bean id="dropBoxManager" class="uk.ac.ebi.pride.archive.submission.util.DropBoxManager">
        <constructor-arg name="dropBoxDetails">
            <list>
                <bean id="dropBoxOne" class="uk.ac.ebi.pride.archive.submission.model.submission.DropBoxDetail">
                    <constructor-arg name="dropBoxDirectory" value="${px.drop.box.one}"/>
                    <constructor-arg name="userName" value="${px.drop.box.one.user}"/>
                    <constructor-arg name="password" value="${px.drop.box.one.password}"/>
                </bean>
                <bean id="dropBoxTwo" class="uk.ac.ebi.pride.archive.submission.model.submission.DropBoxDetail">
                    <constructor-arg name="dropBoxDirectory" value="${px.drop.box.two}"/>
                    <constructor-arg name="userName" value="${px.drop.box.two.user}"/>
                    <constructor-arg name="password" value="${px.drop.box.two.password}"/>
                </bean>
                <bean id="dropBoxThree" class="uk.ac.ebi.pride.archive.submission.model.submission.DropBoxDetail">
                    <constructor-arg name="dropBoxDirectory" value="${px.drop.box.three}"/>
                    <constructor-arg name="userName" value="${px.drop.box.three.user}"/>
                    <constructor-arg name="password" value="${px.drop.box.three.password}"/>
                </bean>
                <bean id="dropBoxFour" class="uk.ac.ebi.pride.archive.submission.model.submission.DropBoxDetail">
                    <constructor-arg name="dropBoxDirectory" value="${px.drop.box.four}"/>
                    <constructor-arg name="userName" value="${px.drop.box.four.user}"/>
                    <constructor-arg name="password" value="${px.drop.box.four.password}"/>
                </bean>
                <bean id="dropBoxFive" class="uk.ac.ebi.pride.archive.submission.model.submission.DropBoxDetail">
                    <constructor-arg name="dropBoxDirectory" value="${px.drop.box.five}"/>
                    <constructor-arg name="userName" value="${px.drop.box.five.user}"/>
                    <constructor-arg name="password" value="${px.drop.box.five.password}"/>
                </bean>
            </list>
        </constructor-arg>
    </bean>

    <bean id="mailSender" class="org.springframework.mail.javamail.JavaMailSenderImpl">
        <property name="host" value="${px.email.host}"/>
    </bean>

    <bean id="templateMessage" class="org.springframework.mail.SimpleMailMessage">
        <property name="to" value="${px.notification.email}"/>
        <property name="subject" value="${px.notification.email.subject}"/>
    </bean>

    <bean id="registrationMailSender" class="org.springframework.mail.javamail.JavaMailSenderImpl">
        <property name="host" value="${px.email.host}"/>
    </bean>

    <bean id="registrationTemplateMessage" class="org.springframework.mail.SimpleMailMessage">
        <property name="to" value="${px.notification.email}"/>
        <property name="subject" value="${px.notification.email.subject}"/>
        <property name="from" value="${px.notification.email}"/>
    </bean>

    <util:properties id="pxProperties" location="classpath:META-INF/props/px.properties"/>

    <context:property-placeholder location="classpath:META-INF/props/*.properties" ignore-unresolvable="true" order="1"/>

</beans>